toolsmanager/__init__.py
toolsmanager/__main__.py
toolsmanager/bases.py
toolsmanager/consts.py
toolsmanager/current_toolsmanager.py
toolsmanager/dbtools.py
toolsmanager/exceptions.py
toolsmanager/functions.py
toolsmanager/printer.py
toolsmanager/tasks.py
toolsmanager/utils.py
toolsmanager/data/append_bashrc.sh
toolsmanager/data/collections.json
toolsmanager/data/tm_bashrc.sh
toolsmanager/data/tools.apt.txt
toolsmanager/data/dbtools/apt.txt
toolsmanager/data/dbtools/collections.json
toolsmanager/data/dbtools/tools.json
toolsmanager-0.1.3.dist-info/LICENSE
toolsmanager-0.1.3.dist-info/METADATA
toolsmanager-0.1.3.dist-info/WHEEL
toolsmanager-0.1.3.dist-info/entry_points.txt
toolsmanager-0.1.3.dist-info/top_level.txt
toolsmanager-0.1.3.dist-info/RECORD
